./.gitignore
./LICENSE
./PKG-INFO
./README.md
./install-mcp-claude-only.sh
./install-mcp-universal-no-git.cmd
./install-mcp-universal-no-git.ps1
./install-mcp-universal-no-git.sh
./install-mcp-universal.cmd
./language.json
./mcp.json
./package_name
./pyproject.toml
./requirements.txt
./test.sh
./test_fastmcp.py
./view_logs.sh
./youtube_transcript_server_fastmcp.py
./docs/tech-sequence-slides.md
./docs/tech-sequence.md
./docs/plans/git-free-install.md
./docs/plans/multi-install-native-fixed.md
./docs/plans/multi-install-native-fixes.md
./docs/plans/multi-install-native.md
./docs/plans/multi-install.md
./docs/research/from-scratch-vs-smithery.md
./docs/research/mcp-clients.md
iflow_mcp_boxabirds_yt_gemini_mcp-1.0.0.dist-info/METADATA
iflow_mcp_boxabirds_yt_gemini_mcp-1.0.0.dist-info/WHEEL
iflow_mcp_boxabirds_yt_gemini_mcp-1.0.0.dist-info/entry_points.txt
iflow_mcp_boxabirds_yt_gemini_mcp-1.0.0.dist-info/licenses/LICENSE
iflow_mcp_boxabirds_yt_gemini_mcp-1.0.0.dist-info/RECORD
