Metadata-Version: 2.4
Name: iflow-mcp-boxabirds-yt-gemini-mcp
Version: 1.0.0
Summary: A Model Context Protocol (MCP) server that enables AI coding assistants to analyze YouTube video transcripts using Gemini API
License-File: LICENSE
Requires-Python: >=3.8
Requires-Dist: fastmcp>=2.8.1
Requires-Dist: google-genai
Requires-Dist: mcp>=1.9.4
